q2sra/__init__.py
q2sra/dada2.py
q2sra/demux.py
q2sra/filter_fastq.py
q2sra/manifest.py
q2sra/merge_metadata.py
q2sra/merge_repseqs.py
q2sra/merge_tables.py
q2sra/prefetch.py
q2sra/proj.py
q2sra/write_metadata.py
q2sra-1.0.0.dist-info/LICENSE
q2sra-1.0.0.dist-info/METADATA
q2sra-1.0.0.dist-info/WHEEL
q2sra-1.0.0.dist-info/top_level.txt
q2sra-1.0.0.dist-info/RECORD
