Metadata-Version: 2.1
Name: q2sra
Version: 1.0.0
Summary: Fetch, process, analyze, and aggregate microbiome sequencing data with SRA Toolkit and QIIME2.
Author: Noah Schulhof
Author-email: Noah Schulhof <nschulhof@u.northwestern.edu>
License: Copyright (c) 2018 The Python Packaging Authority
Project-URL: Homepage, https://github.com/noahschulhof/q2sra
Project-URL: Issues, https://github.com/noahschulhof/q2sra/issues
Keywords: bioinformatics,microbiome
Classifier: Programming Language :: Python :: 3
Requires-Python: >=3.8
License-File: LICENSE
Requires-Dist: pandas >=1.5.3
